func.v
/*
c.	входные параметры a, b, c, d являются целыми числами со знаком (signed)
d.	набор параметров a, b, c, d должен подаваться на вход схемы синхронно 
e.	разрядность данных должна определяться параметром
f.	схема должна обеспечивать возможность получения нового набора входных параметров a, b, c, d каждый такт
g.	латентность схемы должна быть оптимальной
h.	по возможности реализовать подтверждение входных и выходных данных сигналом valid
*/

//Q = ((a-b) * (1+3*c) - 4*d) / 2
module funcQ #(
    parameter DATA_WIDTH = 16
)
(
    input clk,
    input rst,

    input data_vld,
    input signed [DATA_WIDTH-1:0] a,
    input signed [DATA_WIDTH-1:0] b,
    input signed [DATA_WIDTH-1:0] c,
    input signed [DATA_WIDTH-1:0] d,

    output reg Q_vld,
    output reg signed [DATA_WIDTH-1:0] Q
);

reg signed [2*DATA_WIDTH-1:0] tmp1;
reg signed [2*DATA_WIDTH-1:0] tmp2;
reg signed [2*DATA_WIDTH-1:0] tmp3;
reg signed [2*DATA_WIDTH-1:0] tmp4;


reg signed [DATA_WIDTH-1:0] a_r;
reg signed [DATA_WIDTH-1:0] b_r;
reg signed [DATA_WIDTH-1:0] c_r;

reg signed [DATA_WIDTH-1:0] d_r;
reg signed [DATA_WIDTH-1:0] d_r2;
reg signed [DATA_WIDTH-1:0] d_r3;

reg vld_r;
reg vld_r2;
reg vld_r3;
reg vld_r4;

always_ff @(posedge clk or posedge rst) begin
	if (rst) begin
		tmp1 <= 0;
		tmp2 <= 0;
		tmp3 <= 0;
		tmp4 <= 0;
		Q <= 0;
		Q_vld <= 0;
		
		a_r <= 0;
		b_r <= 0;
		c_r <= 0;
		d_r <= 0;
		d_r2 <= 0;
		
		vld_r <= 0;
		vld_r2 <= 0;
		vld_r3 <= 0;
	end
	else begin	// more energy efficient but more area
		if (data_vld) begin
			a_r <= a;
			b_r <= b;
			c_r <= c;
			d_r <= d;
		end
		vld_r <= data_vld;
		
		if (vld_r) begin
			tmp1 <= a_r - b_r;
			tmp2 <= 1 + 3 * c_r;
			d_r2 <= d_r;
		end
		vld_r2 <= vld_r;
		
		if (vld_r2) begin
			tmp3 <= tmp1 * tmp2;
			d_r3 <= d_r2;
		end
		vld_r3 <= vld_r2;
		
		if (vld_r3) begin
			tmp4 <= tmp3 - (4 * d_r3);
		end
		vld_r4 <= vld_r3;
		
		if (vld_r4) begin
			Q <= tmp4 >>> 1;
			Q_vld <= 1;
		end else begin
			Q_vld <= 0;
		end

	end
end

/*
always_ff @(posedge clk or posedge rst) begin	// less area and less energy efficient
	if (rst) begin
		tmp1 <= 0;
		tmp2 <= 0;
		tmp3 <= 0;
		tmp4 <= 0;
		Q <= 0;
		Q_vld <= 0;
		
		a_r <= 0;
		b_r <= 0;
		c_r <= 0;
		d_r <= 0;
		d_r2 <= 0;
		
		vld_r <= 0;
		vld_r2 <= 0;
		vld_r3 <= 0;
	end
	else begin
		a_r <= a;
		b_r <= b;
		c_r <= c;
		d_r <= d;
		vld_r <= data_vld;
		
		tmp1 <= a_r - b_r;
		tmp2 <= 1 + 3 * c_r;
		d_r2 <= d_r;
		vld_r2 <= vld_r;
		
		tmp3 <= tmp1 * tmp2;
		d_r3 <= d_r2;
		vld_r3 <= vld_r2;
		
		tmp4 <= tmp3 - (4 * d_r3);
		vld_r4 <= vld_r3;
		
		Q <= tmp4 >>> 1;
		Q_vld <= vld_r4;
	end
end
*/

endmodule

testbench.sv
`include "func.v"
`include "ref.svf"

module tb_funcQ;

parameter DATA_WIDTH = 16;

logic clk;
logic rst;


logic data_vld;
logic signed [DATA_WIDTH-1:0] a, b, c, d;
logic Q_vld;
logic signed [DATA_WIDTH-1:0] Q;


funcQ #(.DATA_WIDTH(DATA_WIDTH)) DUT (.* );

initial clk <= 0;
always #5 clk <= ~clk;

initial begin
	rst <= 1;
	repeat (10) begin
		@(posedge clk)
		rst <= 0;
	end
end

initial begin
	// Настройка waveform
	// Необходимо для создание временных диаграмм 
	$dumpvars();
//	$dumpvars(0, tbrt_map_gray); 

	#10000 $finish;
end


// hardcoded tests
reg signed [DATA_WIDTH-1:0] a1 = 11, b1 = 5, c1 = -1, d1 = 5;

reg signed [DATA_WIDTH-1:0] a2 = 12, b2 = 3, c2 = -2, d2 = 1;
	
	
initial begin
    repeat (4) begin
        @(posedge clk);
        data_vld <= 0;
        a <= 0; b <= 0; c <= 0; d <= 0;
    end

    @(posedge clk);
    data_vld <= 1;
    a <= 11; b <= 5; c <= -1; d <= 5;
    //signed [DATA_WIDTH-1:0] a1 = 11, b1 = 5, c1 = -1, d1 = 5;

    @(posedge clk);
    a <= 12; b <= 3; c <= -2; d <= 1;
    //signed [DATA_WIDTH-1:0] a2 = 12, b2 = 3, c2 = -2, d2 = 1;

    @(posedge clk);
    data_vld <= 0;
    a <= 0; b <= 0; c <= 0; d <= 0;
end

initial begin
    check_result(a1, b1, c1, d1);
    check_result(a2, b2, c2, d2);

    $finish;
end


task automatic check_result;
    input signed [DATA_WIDTH-1:0] a_in;
    input signed [DATA_WIDTH-1:0] b_in;
    input signed [DATA_WIDTH-1:0] c_in;
    input signed [DATA_WIDTH-1:0] d_in;

    reg signed [DATA_WIDTH-1:0] expected;
    begin
        expected = ref_funcQ(a_in, b_in, c_in, d_in);

        @(posedge clk);
        wait (Q_vld);

        if (Q !== expected)
            $display("FAIL: expected %0d, got %0d", expected, Q);
        else
            $display("PASS: Q = %0d", Q);

        @(posedge clk);
        wait (!Q_vld);
    end
endtask


endmodule

dump.vcd
$date
	Wed May  7 02:12:27 2025
$end
$version
	Icarus Verilog
$end
$timescale
	1s
$end
$scope module tb_funcQ $end
$var wire 1 ! Q_vld $end
$var wire 16 " Q [15:0] $end
$var parameter 32 # DATA_WIDTH $end
$var reg 16 $ a [15:0] $end
$var reg 16 % a1 [15:0] $end
$var reg 16 & a2 [15:0] $end
$var reg 16 ' b [15:0] $end
$var reg 16 ( b1 [15:0] $end
$var reg 16 ) b2 [15:0] $end
$var reg 16 * c [15:0] $end
$var reg 16 + c1 [15:0] $end
$var reg 16 , c2 [15:0] $end
$var reg 1 - clk $end
$var reg 16 . d [15:0] $end
$var reg 16 / d1 [15:0] $end
$var reg 16 0 d2 [15:0] $end
$var reg 1 1 data_vld $end
$var reg 1 2 rst $end
$scope module DUT $end
$var wire 16 3 a [15:0] $end
$var wire 16 4 b [15:0] $end
$var wire 16 5 c [15:0] $end
$var wire 1 - clk $end
$var wire 16 6 d [15:0] $end
$var wire 1 1 data_vld $end
$var wire 1 2 rst $end
$var parameter 32 7 DATA_WIDTH $end
$var reg 16 8 Q [15:0] $end
$var reg 1 ! Q_vld $end
$var reg 16 9 a_r [15:0] $end
$var reg 16 : b_r [15:0] $end
$var reg 16 ; c_r [15:0] $end
$var reg 16 < d_r [15:0] $end
$var reg 16 = d_r2 [15:0] $end
$var reg 16 > d_r3 [15:0] $end
$var reg 32 ? tmp1 [31:0] $end
$var reg 32 @ tmp2 [31:0] $end
$var reg 32 A tmp3 [31:0] $end
$var reg 32 B tmp4 [31:0] $end
$var reg 1 C vld_r $end
$var reg 1 D vld_r2 $end
$var reg 1 E vld_r3 $end
$var reg 1 F vld_r4 $end
$upscope $end
$scope task check_result $end
$upscope $end
$upscope $end
$enddefinitions $end
$comment Show the parameter values. $end
$dumpall
b10000 7
b10000 #
$end
#0
$dumpvars
xF
0E
0D
0C
b0 B
b0 A
b0 @
b0 ?
bx >
b0 =
b0 <
b0 ;
b0 :
b0 9
b0 8
bx 6
bx 5
bx 4
bx 3
12
x1
b1 0
b101 /
bx .
0-
b1111111111111110 ,
b1111111111111111 +
bx *
b11 )
b101 (
bx '
b1100 &
b1011 %
bx $
b0 "
0!
$end
#5
02
b0 .
b0 6
b0 *
b0 5
b0 '
b0 4
b0 $
b0 3
01
1-
#10
0-
#15
0F
1-
#20
0-
#25
1-
#30
0-
#35
1-
#40
0-
#45
b101 .
b101 6
b1111111111111111 *
b1111111111111111 5
b101 '
b101 4
b1011 $
b1011 3
11
1-
#50
0-
#55
1C
b101 <
b1111111111111111 ;
b101 :
b1011 9
b1 .
b1 6
b1111111111111110 *
b1111111111111110 5
b11 '
b11 4
b1100 $
b1100 3
1-
#60
0-
#65
1D
b101 =
b11111111111111111111111111111110 @
b110 ?
b1 <
b1111111111111110 ;
b11 :
b1100 9
b0 .
b0 6
b0 *
b0 5
b0 '
b0 4
b0 $
b0 3
01
1-
#70
0-
#75
1E
b101 >
b11111111111111111111111111110100 A
b1 =
b11111111111111111111111111111011 @
b1001 ?
0C
1-
#80
0-
#85
1F
b11111111111111111111111111100000 B
b1 >
b11111111111111111111111111010011 A
0D
1-
#90
0-
#95
1!
b1111111111110000 "
b1111111111110000 8
b11111111111111111111111111001111 B
0E
1-
#100
0-
#105
b1111111111100111 "
b1111111111100111 8
0F
1-
#110
0-
#115
0!
1-
